django_scripts/__init__.py
django_scripts/dj.py
django_scripts-2.0.dist-info/AUTHORS
django_scripts-2.0.dist-info/LICENSE
django_scripts-2.0.dist-info/METADATA
django_scripts-2.0.dist-info/WHEEL
django_scripts-2.0.dist-info/entry_points.txt
django_scripts-2.0.dist-info/top_level.txt
django_scripts-2.0.dist-info/RECORD
